pydeco/__init__.py
pydeco/config.yml
pydeco/decorator.py
pydeco/utils/__init__.py
pydeco/utils/misc.py
pydeco/utils/parser.py
pydeco/utils/register.py
pydeco-0.363.dist-info/LICENSE
pydeco-0.363.dist-info/METADATA
pydeco-0.363.dist-info/WHEEL
pydeco-0.363.dist-info/top_level.txt
pydeco-0.363.dist-info/RECORD
