Metadata-Version: 2.1
Name: pydeco
Version: 0.363
Summary: Python Class Methods Decorator
Home-page: https://github.com/paulroujansky/pydeco
Author: Paul Roujansky
Author-email: paul@roujansky.eu
License: MIT
Platform: UNKNOWN
Classifier: Programming Language :: Python :: 3
Classifier: License :: OSI Approved :: MIT License
Classifier: Operating System :: OS Independent
Requires-Python: >=3
Requires-Dist: codecov
Requires-Dist: pytest
Requires-Dist: pytest-cov
Requires-Dist: coverage
Requires-Dist: numpydoc
Requires-Dist: sphinx
Requires-Dist: sphinx-bootstrap-theme
Requires-Dist: sphinx-gallery
Requires-Dist: joblib
Requires-Dist: pyyaml
